{"2400000000":[["142","IL","","Y864","A származási igazolásban az szerepel, hogy a származó helyzetet eredményező előá","2023.05.16","","EU"],["695","1011","","Y155","Az Oroszországi Föderációból vagy Belaruszból közvetlenül vagy közvetve exportál","2025.07.20","","EU"],["760","UA","","N954","EUR.1 Szállítási bizonyítvány","2026.06.24","","EU"],["760","UA","","N864","Valamely exportőr által a számlán vagy más kereskedelmi dokumentumon tett számla","2026.06.24","","EU"],["760","UA","","Y997","Az áruk nem Krímből vagy Szevasztopolból származnak vagy nem oda irányulnak (692","2026.06.24","","EU"],["762","UA","","Y984","Nem Ukrajna Donyeck, Kherson, Luhanszk és Zaporizhzhia megyében található, nem k","2026.06.24","","EU"],["762","UA","","N864","Valamely exportőr által a számlán vagy más kereskedelmi dokumentumon tett számla","2026.06.24","","EU"],["762","UA","","N954","EUR.1 Szállítási bizonyítvány","2026.06.24","","EU"],["AAF","N100","X6XX","","","2012.01.01","","HU"],["AAF","N100","X9XX","","","2008.01.01","","HU"]],"2401000000":[["142","1006","","U088","Származási nyilatkozat uniós eredetről, a Kanada és az Európai Unió közötti átfo","2022.01.01","","EU"],["AJA","N100","XXJ7","","","2017.07.01","","HU"],["JEE","N100","","3432","Szárított és fermentált dohány előállító, tároló és kereskedő","2017.07.01","","HU"],["JEE","N100","","3208","Nem engedélyköteles termék","2017.07.01","","HU"]],"2401103510":[["142","5500","","U126","Származásmegjelölő nyilatkozat (az EU-Mercosur ideiglenes kereskedelmi megállapo","2026.05.01","2026.12.31","EU"],["465","1011","","A004","Eredet igazolás dohányhoz","2009.01.01","","EU"]],"2401103520":[["142","5500","","U126","Származásmegjelölő nyilatkozat (az EU-Mercosur ideiglenes kereskedelmi megállapo","2026.05.01","2026.12.31","EU"],["465","1011","","A004","Eredet igazolás dohányhoz","2009.01.01","","EU"]],"2401103591":[["123","1011","","N990","EUS - Meghatározott célra történő felhasználás alkalmazására vonatkozó engedély ","2026.01.01","2026.12.31","EU"],["142","5500","","U126","Származásmegjelölő nyilatkozat (az EU-Mercosur ideiglenes kereskedelmi megállapo","2026.05.01","2026.12.31","EU"]],"2401103599":[["142","5500","","U126","Származásmegjelölő nyilatkozat (az EU-Mercosur ideiglenes kereskedelmi megállapo","2026.05.01","2026.12.31","EU"]],"2401106000":[["142","5500","","U126","Származásmegjelölő nyilatkozat (az EU-Mercosur ideiglenes kereskedelmi megállapo","2026.05.01","2026.12.31","EU"]],"2401107000":[["142","5500","","U126","Származásmegjelölő nyilatkozat (az EU-Mercosur ideiglenes kereskedelmi megállapo","2026.05.01","2026.12.31","EU"]],"2401107010":[["123","1011","","N990","EUS - Meghatározott célra történő felhasználás alkalmazására vonatkozó engedély ","2026.01.01","2026.12.31","EU"]],"2401108510":[["142","5500","","U126","Származásmegjelölő nyilatkozat (az EU-Mercosur ideiglenes kereskedelmi megállapo","2026.05.01","2026.12.31","EU"],["465","1011","","A004","Eredet igazolás dohányhoz","2009.01.01","","EU"]],"2401108590":[["142","5500","","U126","Származásmegjelölő nyilatkozat (az EU-Mercosur ideiglenes kereskedelmi megállapo","2026.05.01","2026.12.31","EU"]],"2401109511":[["123","1011","","N990","EUS - Meghatározott célra történő felhasználás alkalmazására vonatkozó engedély ","2026.01.01","2026.12.31","EU"],["142","5500","","U126","Származásmegjelölő nyilatkozat (az EU-Mercosur ideiglenes kereskedelmi megállapo","2026.05.01","2026.12.31","EU"],["465","1011","","A004","Eredet igazolás dohányhoz","2009.01.01","","EU"]],"2401109519":[["142","5500","","U126","Származásmegjelölő nyilatkozat (az EU-Mercosur ideiglenes kereskedelmi megállapo","2026.05.01","2026.12.31","EU"],["465","1011","","A004","Eredet igazolás dohányhoz","2009.01.01","","EU"]],"2401109521":[["123","1011","","N990","EUS - Meghatározott célra történő felhasználás alkalmazására vonatkozó engedély ","2026.01.01","2026.12.31","EU"],["142","5500","","U126","Származásmegjelölő nyilatkozat (az EU-Mercosur ideiglenes kereskedelmi megállapo","2026.05.01","2026.12.31","EU"],["465","1011","","A004","Eredet igazolás dohányhoz","2009.01.01","","EU"]],"2401109529":[["142","5500","","U126","Származásmegjelölő nyilatkozat (az EU-Mercosur ideiglenes kereskedelmi megállapo","2026.05.01","2026.12.31","EU"],["465","1011","","A004","Eredet igazolás dohányhoz","2009.01.01","","EU"]],"2401109591":[["123","1011","","N990","EUS - Meghatározott célra történő felhasználás alkalmazására vonatkozó engedély ","2026.01.01","2026.12.31","EU"],["142","5500","","U126","Származásmegjelölő nyilatkozat (az EU-Mercosur ideiglenes kereskedelmi megállapo","2026.05.01","2026.12.31","EU"]],"2401109599":[["142","5500","","U126","Származásmegjelölő nyilatkozat (az EU-Mercosur ideiglenes kereskedelmi megállapo","2026.05.01","2026.12.31","EU"]],"2401203510":[["142","5500","","U126","Származásmegjelölő nyilatkozat (az EU-Mercosur ideiglenes kereskedelmi megállapo","2026.05.01","2026.12.31","EU"],["465","1011","","A004","Eredet igazolás dohányhoz","2009.01.01","","EU"]],"2401203520":[["142","5500","","U126","Származásmegjelölő nyilatkozat (az EU-Mercosur ideiglenes kereskedelmi megállapo","2026.05.01","2026.12.31","EU"],["465","1011","","A004","Eredet igazolás dohányhoz","2009.01.01","","EU"]],"2401203591":[["123","1011","","N990","EUS - Meghatározott célra történő felhasználás alkalmazására vonatkozó engedély ","2026.01.01","2026.12.31","EU"],["142","5500","","U126","Származásmegjelölő nyilatkozat (az EU-Mercosur ideiglenes kereskedelmi megállapo","2026.05.01","2026.12.31","EU"]],"2401203599":[["142","5500","","U126","Származásmegjelölő nyilatkozat (az EU-Mercosur ideiglenes kereskedelmi megállapo","2026.05.01","2026.12.31","EU"]],"2401206000":[["142","5500","","U126","Származásmegjelölő nyilatkozat (az EU-Mercosur ideiglenes kereskedelmi megállapo","2026.05.01","2026.12.31","EU"]],"2401207000":[["142","5500","","U126","Származásmegjelölő nyilatkozat (az EU-Mercosur ideiglenes kereskedelmi megállapo","2026.05.01","2026.12.31","EU"]],"2401207010":[["123","1011","","N990","EUS - Meghatározott célra történő felhasználás alkalmazására vonatkozó engedély ","2026.01.01","2026.12.31","EU"]],"2401208510":[["142","5500","","U126","Származásmegjelölő nyilatkozat (az EU-Mercosur ideiglenes kereskedelmi megállapo","2026.05.01","2026.12.31","EU"],["465","1011","","A004","Eredet igazolás dohányhoz","2009.01.01","","EU"]],"2401208590":[["142","5500","","U126","Származásmegjelölő nyilatkozat (az EU-Mercosur ideiglenes kereskedelmi megállapo","2026.05.01","2026.12.31","EU"]],"2401209511":[["123","1011","","N990","EUS - Meghatározott célra történő felhasználás alkalmazására vonatkozó engedély ","2026.01.01","2026.12.31","EU"],["142","5500","","U126","Származásmegjelölő nyilatkozat (az EU-Mercosur ideiglenes kereskedelmi megállapo","2026.05.01","2026.12.31","EU"],["465","1011","","A004","Eredet igazolás dohányhoz","2009.01.01","","EU"]],"2401209519":[["142","5500","","U126","Származásmegjelölő nyilatkozat (az EU-Mercosur ideiglenes kereskedelmi megállapo","2026.05.01","2026.12.31","EU"],["465","1011","","A004","Eredet igazolás dohányhoz","2009.01.01","","EU"]],"2401209521":[["123","1011","","N990","EUS - Meghatározott célra történő felhasználás alkalmazására vonatkozó engedély ","2026.01.01","2026.12.31","EU"],["142","5500","","U126","Származásmegjelölő nyilatkozat (az EU-Mercosur ideiglenes kereskedelmi megállapo","2026.05.01","2026.12.31","EU"],["465","1011","","A004","Eredet igazolás dohányhoz","2009.01.01","","EU"]],"2401209529":[["142","5500","","U126","Származásmegjelölő nyilatkozat (az EU-Mercosur ideiglenes kereskedelmi megállapo","2026.05.01","2026.12.31","EU"],["465","1011","","A004","Eredet igazolás dohányhoz","2009.01.01","","EU"]],"2401209591":[["123","1011","","N990","EUS - Meghatározott célra történő felhasználás alkalmazására vonatkozó engedély ","2026.01.01","2026.12.31","EU"],["142","5500","","U126","Származásmegjelölő nyilatkozat (az EU-Mercosur ideiglenes kereskedelmi megállapo","2026.05.01","2026.12.31","EU"]],"2401209599":[["142","5500","","U126","Származásmegjelölő nyilatkozat (az EU-Mercosur ideiglenes kereskedelmi megállapo","2026.05.01","2026.12.31","EU"]],"2401300000":[["142","5500","","U126","Származásmegjelölő nyilatkozat (az EU-Mercosur ideiglenes kereskedelmi megállapo","2026.05.01","2026.12.31","EU"],["755","1011","","C672","A hulladékszállítmányokat kísérő, az 2024/1157/EU rendelet említett információs ","2026.05.21","","EU"],["755","1011","","C669","A 2024/1157/EU rendelet Tanácsi Rendeletben említett bejelentőlap - 5. cikk és m","2026.05.21","","EU"],["755","1011","","Y923","Az 2024/1157/EU rendelet rendelkezéseinek hatálya alá nem tartozó termék.","2026.05.21","","EU"],["755","1011","","C672","A hulladékszállítmányokat kísérő, az 2024/1157/EU rendelet említett információs ","2026.05.21","","EU"],["755","1011","","C670","A 2024/1157/EU rendelet Tanácsi Rendeletben említett kísérődokumentum - 5. cikk ","2026.05.21","","EU"],["755","1011","","Y923","Az 2024/1157/EU rendelet rendelkezéseinek hatálya alá nem tartozó termék.","2026.05.21","","EU"]],"2402000000":[["142","1006","","U088","Származási nyilatkozat uniós eredetről, a Kanada és az Európai Unió közötti átfo","2022.01.01","","EU"],["760","BY","","L152","Behozatali engedély a 765/2006/EU tanácsi rendelet 1ra. cikke (10) bekezdése ala","2025.02.25","","EU"],["760","BY","","Y728","A 765/2006/EU tanácsi rendelet 1ra. cikkének (1) bekezdésében meghatározott tila","2025.02.25","","EU"],["760","BY","","Y870","Az EU vámuniójának területére beléptetett és a vámhatóságoknak a jelen szankció ","2025.02.25","","EU"],["760","BY","","Y727","A 765/2006/EU tanácsi rendelet 1ra. cikkének (1) bekezdésében meghatározott tila","2025.02.25","","EU"],["762","RU","","L142","Behozatali engedély a 833/2014/EU tanácsi rendelet 3i. cikke (3c) bekezdése alap","2023.12.19","2026.12.31","EU"],["762","RU","","Y874","A 833/2014/EU tanácsi rendelet 3i. cikkének (1) bekezdésében meghatározott tilal","2023.12.19","2026.12.31","EU"],["762","RU","","L143","Behozatali engedély a 833/2014/EU tanácsi rendelet 12 b. cikkének (2) bekezdése ","2023.12.19","2026.12.31","EU"],["762","RU","","Y859","Az EU vámuniójának területére beléptetett és a vámhatóságoknak a jelen szankció ","2023.12.19","2026.12.31","EU"],["AJA","N100","XXJ8","","","2017.07.01","","HU"],["AJA","N100","XXJ9","","","2017.07.01","","HU"],["JEE","N100","","3215","Bejegyzett feladói engedély","2017.07.01","","HU"],["JEE","N100","","3208","Nem engedélyköteles termék","2017.07.01","","HU"],["JEE","N100","","3182","Jövedéki engedély","2017.07.01","","HU"],["JEE","N100","","3184","Adóraktári engedély","2017.07.01","","HU"]],"2402100000":[["142","2014","","Y021","EGT kedvezményes elbánás iránti kérelem","2018.05.01","","EU"],["142","2012","","Y021","EGT kedvezményes elbánás iránti kérelem","2018.05.01","","EU"],["142","5500","","U126","Származásmegjelölő nyilatkozat (az EU-Mercosur ideiglenes kereskedelmi megállapo","2026.05.01","2026.12.31","EU"],["728","KP","","Y946","Áruk, amelyek a nemzetközi jog szerint mentességet élvező, a tagállamoknak a KND","2018.02.01","","EU"],["728","KP","","Y945","Az utazók személyes használati tárgyai, illetve a nem kereskedelmi természetű, a","2018.02.01","","EU"],["AJA","N100","XXD1","","","2026.01.01","","HU"],["AJA","N100","XXDA","","","2026.01.01","","HU"]],"2402201000":[["142","2012","","Y021","EGT kedvezményes elbánás iránti kérelem","2017.09.21","","EU"],["142","5500","","U126","Származásmegjelölő nyilatkozat (az EU-Mercosur ideiglenes kereskedelmi megállapo","2026.05.01","2026.12.31","EU"],["143","KR","","U059","Származási igazolás, amely a következő angol nyelvű nyilatkozatot tartalmazza: \"","2026.07.01","2027.06.30","EU"]],"2402209000":[["142","2012","","Y021","EGT kedvezményes elbánás iránti kérelem","2018.05.01","","EU"],["142","2014","","Y021","EGT kedvezményes elbánás iránti kérelem","2018.05.01","","EU"],["142","5500","","U126","Származásmegjelölő nyilatkozat (az EU-Mercosur ideiglenes kereskedelmi megállapo","2026.05.01","2026.12.31","EU"],["143","KR","","U059","Származási igazolás, amely a következő angol nyelvű nyilatkozatot tartalmazza: \"","2026.07.01","2027.06.30","EU"]],"2402900000":[["142","2014","","Y021","EGT kedvezményes elbánás iránti kérelem","2018.05.01","","EU"],["142","2012","","Y021","EGT kedvezményes elbánás iránti kérelem","2018.05.01","","EU"],["142","5500","","U126","Származásmegjelölő nyilatkozat (az EU-Mercosur ideiglenes kereskedelmi megállapo","2026.05.01","2026.12.31","EU"],["728","KP","","Y945","Az utazók személyes használati tárgyai, illetve a nem kereskedelmi természetű, a","2018.02.01","","EU"],["728","KP","","Y946","Áruk, amelyek a nemzetközi jog szerint mentességet élvező, a tagállamoknak a KND","2018.02.01","","EU"],["AJA","N100","XXDC","","","2026.01.01","","HU"],["AJA","N100","XXDB","","","2026.01.01","","HU"],["AJA","N100","XXDD","","","2026.01.01","","HU"]],"2403000000":[["142","2014","","Y021","EGT kedvezményes elbánás iránti kérelem","2018.05.01","","EU"],["142","1006","","U088","Származási nyilatkozat uniós eredetről, a Kanada és az Európai Unió közötti átfo","2022.01.01","","EU"]],"2403110000":[["142","2012","","Y021","EGT kedvezményes elbánás iránti kérelem","2018.05.01","","EU"],["142","5500","","U126","Származásmegjelölő nyilatkozat (az EU-Mercosur ideiglenes kereskedelmi megállapo","2026.05.01","2026.12.31","EU"],["AJA","N100","XXDE","","","2026.01.01","","HU"],["AJA","N100","XXJ9","","","2017.07.01","","HU"],["AJA","N100","XXDF","","","2026.01.01","","HU"],["AJA","N100","XXJ8","","","2017.07.01","","HU"],["JEE","N100","","3182","Jövedéki engedély","2017.07.01","","HU"],["JEE","N100","","3184","Adóraktári engedély","2017.07.01","","HU"],["JEE","N100","","3215","Bejegyzett feladói engedély","2017.07.01","","HU"],["JEE","N100","","3208","Nem engedélyköteles termék","2017.07.01","","HU"]],"2403190000":[["142","2012","","Y021","EGT kedvezményes elbánás iránti kérelem","2018.05.01","","EU"],["AJA","N100","XXJ9","","","2017.07.01","","HU"],["AJA","N100","XXDF","","","2026.01.01","","HU"],["AJA","N100","XXJ8","","","2017.07.01","","HU"],["AJA","N100","XXDE","","","2026.01.01","","HU"],["AJA","N100","XXD6","","","2026.01.01","","HU"],["AJA","N100","XXD5","","","2026.01.01","","HU"],["JEE","N100","","3184","Adóraktári engedély","2017.07.01","","HU"],["JEE","N100","","3215","Bejegyzett feladói engedély","2017.07.01","","HU"],["JEE","N100","","3182","Jövedéki engedély","2017.07.01","","HU"],["JEE","N100","","3208","Nem engedélyköteles termék","2017.07.01","","HU"]],"2403191000":[["142","5500","","U126","Származásmegjelölő nyilatkozat (az EU-Mercosur ideiglenes kereskedelmi megállapo","2026.05.01","2026.12.31","EU"]],"2403199000":[["142","5500","","U126","Származásmegjelölő nyilatkozat (az EU-Mercosur ideiglenes kereskedelmi megállapo","2026.05.01","2026.12.31","EU"]],"2403910000":[["142","5500","","U126","Származásmegjelölő nyilatkozat (az EU-Mercosur ideiglenes kereskedelmi megállapo","2026.05.01","2026.12.31","EU"],["142","2012","","Y021","EGT kedvezményes elbánás iránti kérelem","2018.05.01","","EU"]],"2403991000":[["142","2012","","Y021","EGT kedvezményes elbánás iránti kérelem","2018.05.01","","EU"],["142","5500","","U126","Származásmegjelölő nyilatkozat (az EU-Mercosur ideiglenes kereskedelmi megállapo","2026.05.01","2026.12.31","EU"],["JEE","N100","","3208","Nem engedélyköteles termék","2020.03.01","","HU"],["JEE","N100","","3182","Jövedéki engedély","2020.03.01","","HU"],["JEE","N100","","3184","Adóraktári engedély","2020.03.01","","HU"],["JEE","N100","","3215","Bejegyzett feladói engedély","2020.03.01","","HU"]],"2403999000":[["142","2012","","Y021","EGT kedvezményes elbánás iránti kérelem","2018.05.01","","EU"],["142","5500","","U126","Származásmegjelölő nyilatkozat (az EU-Mercosur ideiglenes kereskedelmi megállapo","2026.05.01","2026.12.31","EU"],["AJA","N100","XXD9","","","2026.01.01","","HU"],["AJA","N100","XXD7","","","2026.01.01","","HU"],["AJA","N100","XXJ9","","","2017.07.01","","HU"],["AJA","N100","XXJ7","","","2017.07.01","","HU"],["AJA","N100","XXD8","","","2026.01.01","","HU"],["AJA","N100","XXJ8","","","2017.07.01","","HU"],["JEE","N100","","3182","Jövedéki engedély","2017.07.01","","HU"],["JEE","N100","","3184","Adóraktári engedély","2017.07.01","","HU"],["JEE","N100","","3208","Nem engedélyköteles termék","2017.07.01","","HU"],["JEE","N100","","3215","Bejegyzett feladói engedély","2017.07.01","","HU"]],"2404110000":[["142","1006","","U088","Származási nyilatkozat uniós eredetről, a Kanada és az Európai Unió közötti átfo","2022.01.01","","EU"],["142","2014","","Y021","EGT kedvezményes elbánás iránti kérelem","2022.01.01","","EU"],["142","5500","","U126","Származásmegjelölő nyilatkozat (az EU-Mercosur ideiglenes kereskedelmi megállapo","2026.05.01","2026.12.31","EU"],["AJA","N100","XXJ8","","","2022.01.01","","HU"],["AJA","N100","XXD8","","","2026.01.01","","HU"],["AJA","N100","XXJ9","","","2022.01.01","","HU"],["AJA","N100","XXDI","","","2026.01.01","","HU"],["AJA","N100","XXDJ","","","2026.01.01","","HU"],["JEE","N100","","3208","Nem engedélyköteles termék","2022.01.01","","HU"],["JEE","N100","","3184","Adóraktári engedély","2022.01.01","","HU"],["JEE","N100","","3182","Jövedéki engedély","2022.01.01","","HU"],["JEE","N100","","3215","Bejegyzett feladói engedély","2022.01.01","","HU"]],"2404110010":[["142","2012","","Y021","EGT kedvezményes elbánás iránti kérelem","2022.01.01","","EU"]],"2404110090":[["142","2012","","Y021","EGT kedvezményes elbánás iránti kérelem","2022.01.01","","EU"]],"2404120000":[["142","1006","","U088","Származási nyilatkozat uniós eredetről, a Kanada és az Európai Unió közötti átfo","2022.01.01","","EU"],["142","5500","","U126","Származásmegjelölő nyilatkozat (az EU-Mercosur ideiglenes kereskedelmi megállapo","2026.05.01","2026.12.31","EU"],["714","IR","","Y949","az intézkedéshez kapcsolódó lábjegyzetekben szereplőktől eltérő áruk (267/2012/ ","2025.09.30","","EU"],["714","1011","","Y069","Nem Iránban feladott áruk","2022.01.01","","EU"],["714","1011","","C067","Korlátozás alá tartozó árukra és technológiákra vonatkozó behozatali engedély (2","2022.01.01","","EU"],["714","1011","","Y949","az intézkedéshez kapcsolódó lábjegyzetekben szereplőktől eltérő áruk (267/2012/ ","2022.01.01","","EU"],["AJA","N100","XXD7","","","2026.01.01","","HU"],["AJA","N100","XXJ9","","","2022.01.01","","HU"],["AJA","N100","XXDJ","","","2026.01.01","","HU"],["AJA","N100","XXJ8","","","2022.01.01","","HU"],["AJA","N100","XXDI","","","2026.01.01","","HU"],["AJA","N100","XXD9","","","2026.01.01","","HU"],["JEE","N100","","3182","Jövedéki engedély","2022.01.01","","HU"],["JEE","N100","","3184","Adóraktári engedély","2022.01.01","","HU"],["JEE","N100","","3215","Bejegyzett feladói engedély","2022.01.01","","HU"],["JEE","N100","","3208","Nem engedélyköteles termék","2022.01.01","","HU"]],"2404120010":[["142","1007","","U090","szállítási bizonyítvány - EUR-MED szállítási bizonyítvány (feltéve, hogy a 7. ro","2022.01.01","","EU"],["142","1007","","U091","Számlanyilatkozat - EUR-MED számlanyilatkozat (feltéve, hogy a nyilatkozat tarta","2022.01.01","","EU"],["142","2012","","Y021","EGT kedvezményes elbánás iránti kérelem","2022.01.01","","EU"],["475","1011","3200","","","2022.01.01","","EU"],["475","1011","3200","L135","A behozatali engedélyt (prekurzorok) annak a tagállamnak az illetékes hatósága b","2022.01.01","","EU"],["475","1011","3249","","","2022.01.01","","EU"]],"2404120090":[["142","1007","","U090","szállítási bizonyítvány - EUR-MED szállítási bizonyítvány (feltéve, hogy a 7. ro","2022.01.01","","EU"],["142","1007","","U091","Számlanyilatkozat - EUR-MED számlanyilatkozat (feltéve, hogy a nyilatkozat tarta","2022.01.01","","EU"],["142","2012","","Y021","EGT kedvezményes elbánás iránti kérelem","2022.01.01","","EU"],["465","KP","","Y944","Az (EU) 2017/1509 rendelet VI. mellékletében felsoroltaktól (kőolajtermékek) elt","2022.01.01","","EU"],["475","1011","3200","L135","A behozatali engedélyt (prekurzorok) annak a tagállamnak az illetékes hatósága b","2022.01.01","","EU"],["475","1011","3249","","","2022.01.01","","EU"],["475","1011","3200","","","2022.01.01","","EU"],["711","IR","","Y966","Az intézkedéshez kapcsolódó „MG” lábjegyzetekben felsoroltaktól (az (EU) 267/201","2022.01.01","","EU"],["755","1011","","C670","A 2024/1157/EU rendelet Tanácsi Rendeletben említett kísérődokumentum - 5. cikk ","2026.05.21","","EU"],["755","1011","","C672","A hulladékszállítmányokat kísérő, az 2024/1157/EU rendelet említett információs ","2026.05.21","","EU"],["755","1011","","Y923","Az 2024/1157/EU rendelet rendelkezéseinek hatálya alá nem tartozó termék.","2026.05.21","","EU"],["755","1011","","C669","A 2024/1157/EU rendelet Tanácsi Rendeletben említett bejelentőlap - 5. cikk és m","2026.05.21","","EU"],["755","1011","","C672","A hulladékszállítmányokat kísérő, az 2024/1157/EU rendelet említett információs ","2026.05.21","","EU"],["755","1011","","Y923","Az 2024/1157/EU rendelet rendelkezéseinek hatálya alá nem tartozó termék.","2026.05.21","","EU"],["AJA","N100","XXJ7","","","2022.01.01","","HU"]],"2404190000":[["142","1006","","U088","Származási nyilatkozat uniós eredetről, a Kanada és az Európai Unió közötti átfo","2022.01.01","","EU"]],"2404191000":[["142","5500","","U126","Származásmegjelölő nyilatkozat (az EU-Mercosur ideiglenes kereskedelmi megállapo","2026.05.01","2026.12.31","EU"],["142","2012","","Y021","EGT kedvezményes elbánás iránti kérelem","2022.01.01","","EU"],["142","2014","","Y021","EGT kedvezményes elbánás iránti kérelem","2022.01.01","","EU"],["AJA","N100","XXDJ","","","2026.01.01","","HU"],["AJA","N100","XXJ8","","","2023.02.01","","HU"],["AJA","N100","XXJ9","","","2023.02.01","","HU"],["AJA","N100","XXDI","","","2026.01.01","","HU"],["JEE","N100","","3184","Adóraktári engedély","2023.02.01","","HU"],["JEE","N100","","3208","Nem engedélyköteles termék","2023.02.01","","HU"],["JEE","N100","","3215","Bejegyzett feladói engedély","2023.02.01","","HU"],["JEE","N100","","3182","Jövedéki engedély","2023.02.01","","HU"]],"2404199000":[["142","1007","","U090","szállítási bizonyítvány - EUR-MED szállítási bizonyítvány (feltéve, hogy a 7. ro","2022.01.01","","EU"],["142","2012","","Y021","EGT kedvezményes elbánás iránti kérelem","2022.01.01","","EU"],["142","1007","","U091","Számlanyilatkozat - EUR-MED számlanyilatkozat (feltéve, hogy a nyilatkozat tarta","2022.01.01","","EU"],["142","5500","","U126","Származásmegjelölő nyilatkozat (az EU-Mercosur ideiglenes kereskedelmi megállapo","2026.05.01","2026.12.31","EU"],["714","IR","","Y949","az intézkedéshez kapcsolódó lábjegyzetekben szereplőktől eltérő áruk (267/2012/ ","2025.09.30","","EU"],["AJA","N100","XXJ8","","","2022.01.01","","HU"],["AJA","N100","XXJ9","","","2022.01.01","","HU"],["AJA","N100","XXD7","","","2026.01.01","","HU"],["AJA","N100","XXD9","","","2026.01.01","","HU"],["AJA","N100","XXDJ","","","2026.01.01","","HU"],["AJA","N100","XXDI","","","2026.01.01","","HU"],["JEE","N100","","3182","Jövedéki engedély","2022.01.01","","HU"],["JEE","N100","","3215","Bejegyzett feladói engedély","2022.01.01","","HU"],["JEE","N100","","3184","Adóraktári engedély","2022.01.01","","HU"],["JEE","N100","","3208","Nem engedélyköteles termék","2022.01.01","","HU"]],"2404910000":[["142","1006","","U088","Származási nyilatkozat uniós eredetről, a Kanada és az Európai Unió közötti átfo","2022.01.01","","EU"]],"2404911000":[["142","2012","","Y021","EGT kedvezményes elbánás iránti kérelem","2022.01.01","","EU"],["142","5500","","U126","Származásmegjelölő nyilatkozat (az EU-Mercosur ideiglenes kereskedelmi megállapo","2026.05.01","2026.12.31","EU"],["143","CA","","C006","Export permit (A Tanács (EU) 2017/37 határozata (HL L 11))","2026.01.01","2026.12.31","EU"],["143","CA","","U062","Hivatkozás az (EU) 2017/37 tanácsi határozat (HL L 11) 5-A. mellékletére","2026.01.01","2026.12.31","EU"]],"2404919000":[["142","2012","","Y021","EGT kedvezményes elbánás iránti kérelem","2022.01.01","","EU"],["142","2014","","Y021","EGT kedvezményes elbánás iránti kérelem","2022.01.01","","EU"],["142","5500","","U126","Származásmegjelölő nyilatkozat (az EU-Mercosur ideiglenes kereskedelmi megállapo","2026.05.01","2026.12.31","EU"],["AJA","N100","XXJ8","","","2022.01.01","","HU"],["AJA","N100","XXDG","","","2026.01.01","","HU"],["AJA","N100","XXJ9","","","2022.01.01","","HU"],["AJA","N100","XXDH","","","2026.01.01","","HU"],["JEE","N100","","3215","Bejegyzett feladói engedély","2022.01.01","","HU"],["JEE","N100","","3184","Adóraktári engedély","2022.01.01","","HU"],["JEE","N100","","3182","Jövedéki engedély","2022.01.01","","HU"],["JEE","N100","","3208","Nem engedélyköteles termék","2022.01.01","","HU"]],"2404920000":[["755","1011","","Y923","Az 2024/1157/EU rendelet rendelkezéseinek hatálya alá nem tartozó termék.","2026.05.21","","EU"],["755","1011","","Y923","Az 2024/1157/EU rendelet rendelkezéseinek hatálya alá nem tartozó termék.","2026.05.21","","EU"],["755","1011","","C670","A 2024/1157/EU rendelet Tanácsi Rendeletben említett kísérődokumentum - 5. cikk ","2026.05.21","","EU"],["755","1011","","C672","A hulladékszállítmányokat kísérő, az 2024/1157/EU rendelet említett információs ","2026.05.21","","EU"],["755","1011","","C669","A 2024/1157/EU rendelet Tanácsi Rendeletben említett bejelentőlap - 5. cikk és m","2026.05.21","","EU"],["755","1011","","C672","A hulladékszállítmányokat kísérő, az 2024/1157/EU rendelet említett információs ","2026.05.21","","EU"]],"2404990000":[["142","5500","","U126","Származásmegjelölő nyilatkozat (az EU-Mercosur ideiglenes kereskedelmi megállapo","2026.05.01","2026.12.31","EU"],["142","1006","","U088","Származási nyilatkozat uniós eredetről, a Kanada és az Európai Unió közötti átfo","2022.01.01","","EU"],["142","1007","","U090","szállítási bizonyítvány - EUR-MED szállítási bizonyítvány (feltéve, hogy a 7. ro","2022.01.01","","EU"],["142","1007","","U091","Számlanyilatkozat - EUR-MED számlanyilatkozat (feltéve, hogy a nyilatkozat tarta","2022.01.01","","EU"],["142","2012","","Y021","EGT kedvezményes elbánás iránti kérelem","2022.01.01","","EU"]],"2402200000":[["AJA","N100","XXDB","","","2026.01.01","","HU"],["AJA","N100","XXDD","","","2026.01.01","","HU"],["AJA","N100","XXD4","","","2026.01.01","","HU"],["AJA","N100","XXD3","","","2026.01.01","","HU"],["AJA","N100","XXD2","","","2026.01.01","","HU"],["AJA","N100","XXDC","","","2026.01.01","","HU"]],"2403990000":[["AJA","N100","XXDG","","","2026.01.01","","HU"]]}