{"3700000000":[["142","IL","","Y864","A származási igazolásban az szerepel, hogy a származó helyzetet eredményező előá","2023.05.16","","EU"],["142","1007","","U091","Számlanyilatkozat - EUR-MED számlanyilatkozat (feltéve, hogy a nyilatkozat tarta","2007.01.01","","EU"],["142","1007","","U090","szállítási bizonyítvány - EUR-MED szállítási bizonyítvány (feltéve, hogy a 7. ro","2007.01.01","","EU"],["142","US","","U190","A(z) 2026/1455/EU rendelet 6. cikkével összhangban megállapított származás igazo","2026.07.01","","EU"],["142","2012","","Y021","EGT kedvezményes elbánás iránti kérelem","2007.07.01","","EU"],["760","UA","","N864","Valamely exportőr által a számlán vagy más kereskedelmi dokumentumon tett számla","2026.06.24","","EU"],["760","UA","","N954","EUR.1 Szállítási bizonyítvány","2026.06.24","","EU"],["760","UA","","Y997","Az áruk nem Krímből vagy Szevasztopolból származnak vagy nem oda irányulnak (692","2026.06.24","","EU"],["762","UA","","N864","Valamely exportőr által a számlán vagy más kereskedelmi dokumentumon tett számla","2026.06.24","","EU"],["762","UA","","N954","EUR.1 Szállítási bizonyítvány","2026.06.24","","EU"],["762","UA","","Y984","Nem Ukrajna Donyeck, Kherson, Luhanszk és Zaporizhzhia megyében található, nem k","2026.06.24","","EU"],["AAF","N100","X9XX","","","2008.01.01","","HU"],["AAF","N100","X6XX","","","2012.01.01","","HU"]],"3701000000":[["142","1006","","U088","Származási nyilatkozat uniós eredetről, a Kanada és az Európai Unió közötti átfo","2017.09.21","","EU"],["748","1008","","Y969","A polgári védelemhez és a katonai célú felhasználásokhoz elengedhetetlen; vagy a","2025.12.31","","EU"],["748","1008","","Y924","Az (EU) 2017/852 rendelet által nem érintett áruk.","2025.12.31","","EU"]],"3701100000":[["142","5500","","U126","Származásmegjelölő nyilatkozat (az EU-Mercosur ideiglenes kereskedelmi megállapo","2026.05.01","2026.12.31","EU"]],"3701200000":[["142","5500","","U126","Származásmegjelölő nyilatkozat (az EU-Mercosur ideiglenes kereskedelmi megállapo","2026.05.01","2026.12.31","EU"]],"3701910000":[["142","5500","","U126","Származásmegjelölő nyilatkozat (az EU-Mercosur ideiglenes kereskedelmi megállapo","2026.05.01","2026.12.31","EU"]],"3702000000":[["142","1006","","U088","Származási nyilatkozat uniós eredetről, a Kanada és az Európai Unió közötti átfo","2017.09.21","","EU"],["748","1008","","Y969","A polgári védelemhez és a katonai célú felhasználásokhoz elengedhetetlen; vagy a","2025.12.31","","EU"],["748","1008","","Y924","Az (EU) 2017/852 rendelet által nem érintett áruk.","2025.12.31","","EU"]],"3702100000":[["142","5500","","U126","Származásmegjelölő nyilatkozat (az EU-Mercosur ideiglenes kereskedelmi megállapo","2026.05.01","2026.12.31","EU"]],"3702319100":[["105","1011","","N990","EUS - Meghatározott célra történő felhasználás alkalmazására vonatkozó engedély ","2007.01.01","","EU"]],"3702319700":[["142","5500","","U126","Származásmegjelölő nyilatkozat (az EU-Mercosur ideiglenes kereskedelmi megállapo","2026.05.01","2026.12.31","EU"]],"3702321000":[["142","5500","","U126","Származásmegjelölő nyilatkozat (az EU-Mercosur ideiglenes kereskedelmi megállapo","2026.05.01","2026.12.31","EU"]],"3702322000":[["142","5500","","U126","Származásmegjelölő nyilatkozat (az EU-Mercosur ideiglenes kereskedelmi megállapo","2026.05.01","2026.12.31","EU"]],"3702328500":[["142","5500","","U126","Származásmegjelölő nyilatkozat (az EU-Mercosur ideiglenes kereskedelmi megállapo","2026.05.01","2026.12.31","EU"]],"3702390000":[["142","5500","","U126","Származásmegjelölő nyilatkozat (az EU-Mercosur ideiglenes kereskedelmi megállapo","2026.05.01","2026.12.31","EU"]],"3702410000":[["142","5500","","U126","Származásmegjelölő nyilatkozat (az EU-Mercosur ideiglenes kereskedelmi megállapo","2026.05.01","2026.12.31","EU"]],"3702420000":[["142","5500","","U126","Származásmegjelölő nyilatkozat (az EU-Mercosur ideiglenes kereskedelmi megállapo","2026.05.01","2026.12.31","EU"]],"3702430000":[["142","5500","","U126","Származásmegjelölő nyilatkozat (az EU-Mercosur ideiglenes kereskedelmi megállapo","2026.05.01","2026.12.31","EU"]],"3702440000":[["142","5500","","U126","Származásmegjelölő nyilatkozat (az EU-Mercosur ideiglenes kereskedelmi megállapo","2026.05.01","2026.12.31","EU"]],"3702520000":[["142","5500","","U126","Származásmegjelölő nyilatkozat (az EU-Mercosur ideiglenes kereskedelmi megállapo","2026.05.01","2026.12.31","EU"]],"3702530000":[["142","5500","","U126","Származásmegjelölő nyilatkozat (az EU-Mercosur ideiglenes kereskedelmi megállapo","2026.05.01","2026.12.31","EU"]],"3702540000":[["142","5500","","U126","Származásmegjelölő nyilatkozat (az EU-Mercosur ideiglenes kereskedelmi megállapo","2026.05.01","2026.12.31","EU"]],"3702550000":[["142","5500","","U126","Származásmegjelölő nyilatkozat (az EU-Mercosur ideiglenes kereskedelmi megállapo","2026.05.01","2026.12.31","EU"]],"3702560000":[["142","5500","","U126","Származásmegjelölő nyilatkozat (az EU-Mercosur ideiglenes kereskedelmi megállapo","2026.05.01","2026.12.31","EU"]],"3702961000":[["142","5500","","U126","Származásmegjelölő nyilatkozat (az EU-Mercosur ideiglenes kereskedelmi megállapo","2026.05.01","2026.12.31","EU"]],"3702969000":[["142","5500","","U126","Származásmegjelölő nyilatkozat (az EU-Mercosur ideiglenes kereskedelmi megállapo","2026.05.01","2026.12.31","EU"]],"3702971000":[["142","5500","","U126","Származásmegjelölő nyilatkozat (az EU-Mercosur ideiglenes kereskedelmi megállapo","2026.05.01","2026.12.31","EU"]],"3702979000":[["142","5500","","U126","Származásmegjelölő nyilatkozat (az EU-Mercosur ideiglenes kereskedelmi megállapo","2026.05.01","2026.12.31","EU"]],"3702980000":[["142","5500","","U126","Származásmegjelölő nyilatkozat (az EU-Mercosur ideiglenes kereskedelmi megállapo","2026.05.01","2026.12.31","EU"]],"3703000000":[["142","1006","","U088","Származási nyilatkozat uniós eredetről, a Kanada és az Európai Unió közötti átfo","2017.09.21","","EU"],["748","1008","","Y969","A polgári védelemhez és a katonai célú felhasználásokhoz elengedhetetlen; vagy a","2025.12.31","","EU"],["748","1008","","Y924","Az (EU) 2017/852 rendelet által nem érintett áruk.","2025.12.31","","EU"]],"3703100000":[["142","5500","","U126","Származásmegjelölő nyilatkozat (az EU-Mercosur ideiglenes kereskedelmi megállapo","2026.05.01","2026.12.31","EU"]],"3703200000":[["142","5500","","U126","Származásmegjelölő nyilatkozat (az EU-Mercosur ideiglenes kereskedelmi megállapo","2026.05.01","2026.12.31","EU"]],"3703900000":[["142","5500","","U126","Származásmegjelölő nyilatkozat (az EU-Mercosur ideiglenes kereskedelmi megállapo","2026.05.01","2026.12.31","EU"]],"3704000000":[["465","SY","4044","","","2025.05.29","","EU"],["465","SY","4098","","","2025.05.29","","EU"],["465","SY","4013","","","2025.05.29","","EU"],["465","IQ","4099","","","2003.05.23","","EU"],["465","IQ","4013","","","2003.05.23","","EU"],["465","IQ","4044","","","2003.05.23","","EU"],["748","1008","","Y969","A polgári védelemhez és a katonai célú felhasználásokhoz elengedhetetlen; vagy a","2025.12.31","","EU"],["748","1008","","Y924","Az (EU) 2017/852 rendelet által nem érintett áruk.","2025.12.31","","EU"]],"3704001000":[["465","KP","","Y970","Az intézkedéshez kapcsolódó „MG” lábjegyzetekben felsoroltaktól (az (EU) 2017/15","2019.07.01","","EU"],["707","KP","","Y971","Az intézkedéshez kapcsolódó „MG” lábjegyzetekben felsoroltaktól (az (EU) 2017/15","2019.07.01","","EU"],["711","IR","","Y966","Az intézkedéshez kapcsolódó „MG” lábjegyzetekben felsoroltaktól (az (EU) 267/201","2017.10.23","","EU"],["711","KP","","Y920","Az intézkedéshez kapcsolt lábjegyzetben szereplő termékektől eltérő termék","2017.09.01","","EU"],["714","1011","","C067","Korlátozás alá tartozó árukra és technológiákra vonatkozó behozatali engedély (2","2017.04.03","","EU"],["714","1011","","Y069","Nem Iránban feladott áruk","2017.04.03","","EU"],["714","1011","","Y949","az intézkedéshez kapcsolódó lábjegyzetekben szereplőktől eltérő áruk (267/2012/ ","2017.04.03","","EU"],["714","IR","","Y949","az intézkedéshez kapcsolódó lábjegyzetekben szereplőktől eltérő áruk (267/2012/ ","2025.09.30","","EU"],["IDU","1008","","0600","Nemzetközi importigazolás köteles kettős felhasználású termék","2020.04.01","","HU"],["IDU","1008","","0572","A kettős felhasználású termék behozatalához nemzetközi importigazolás nem szüksé","2020.04.01","","HU"]],"3704009000":[["142","1006","","U088","Származási nyilatkozat uniós eredetről, a Kanada és az Európai Unió közötti átfo","2017.09.21","","EU"],["142","5500","","U126","Származásmegjelölő nyilatkozat (az EU-Mercosur ideiglenes kereskedelmi megállapo","2026.05.01","2026.12.31","EU"]],"3705000000":[["465","SY","4044","","","2025.05.29","","EU"],["465","IQ","4044","","","2003.05.23","","EU"],["465","SY","4013","","","2025.05.29","","EU"],["465","SY","4098","","","2025.05.29","","EU"],["465","IQ","4099","","","2003.05.23","","EU"],["465","IQ","4013","","","2003.05.23","","EU"],["748","1008","","Y969","A polgári védelemhez és a katonai célú felhasználásokhoz elengedhetetlen; vagy a","2025.12.31","","EU"],["748","1008","","Y924","Az (EU) 2017/852 rendelet által nem érintett áruk.","2025.12.31","","EU"]],"3705001000":[["142","5500","","U126","Származásmegjelölő nyilatkozat (az EU-Mercosur ideiglenes kereskedelmi megállapo","2026.05.01","2026.12.31","EU"],["142","1006","","U088","Származási nyilatkozat uniós eredetről, a Kanada és az Európai Unió közötti átfo","2017.09.21","","EU"]],"3705009000":[["465","KP","","Y970","Az intézkedéshez kapcsolódó „MG” lábjegyzetekben felsoroltaktól (az (EU) 2017/15","2019.07.01","","EU"],["707","KP","","Y971","Az intézkedéshez kapcsolódó „MG” lábjegyzetekben felsoroltaktól (az (EU) 2017/15","2019.07.01","","EU"],["711","IR","","Y966","Az intézkedéshez kapcsolódó „MG” lábjegyzetekben felsoroltaktól (az (EU) 267/201","2017.10.23","","EU"],["711","KP","","Y920","Az intézkedéshez kapcsolt lábjegyzetben szereplő termékektől eltérő termék","2017.09.01","","EU"],["714","1011","","Y949","az intézkedéshez kapcsolódó lábjegyzetekben szereplőktől eltérő áruk (267/2012/ ","2017.04.03","","EU"],["714","1011","","C067","Korlátozás alá tartozó árukra és technológiákra vonatkozó behozatali engedély (2","2017.04.03","","EU"],["714","1011","","Y069","Nem Iránban feladott áruk","2017.04.03","","EU"],["714","IR","","Y949","az intézkedéshez kapcsolódó lábjegyzetekben szereplőktől eltérő áruk (267/2012/ ","2025.09.30","","EU"],["IDU","1008","","0600","Nemzetközi importigazolás köteles kettős felhasználású termék","2020.04.01","","HU"],["IDU","1008","","0572","A kettős felhasználású termék behozatalához nemzetközi importigazolás nem szüksé","2020.04.01","","HU"]],"3706000000":[["465","SY","4044","","","2025.05.29","","EU"],["465","IQ","4099","","","2003.05.23","","EU"],["465","IQ","4013","","","2003.05.23","","EU"],["465","SY","4013","","","2025.05.29","","EU"],["465","SY","4098","","","2025.05.29","","EU"],["465","IQ","4044","","","2003.05.23","","EU"]],"3706109900":[["142","5500","","U126","Származásmegjelölő nyilatkozat (az EU-Mercosur ideiglenes kereskedelmi megállapo","2026.05.01","2026.12.31","EU"],["142","1006","","U088","Származási nyilatkozat uniós eredetről, a Kanada és az Európai Unió közötti átfo","2017.09.21","","EU"]],"3706909900":[["142","5500","","U126","Származásmegjelölő nyilatkozat (az EU-Mercosur ideiglenes kereskedelmi megállapo","2026.05.01","2026.12.31","EU"],["142","1006","","U088","Származási nyilatkozat uniós eredetről, a Kanada és az Európai Unió közötti átfo","2017.09.21","","EU"]],"3707100000":[["142","1006","","U088","Származási nyilatkozat uniós eredetről, a Kanada és az Európai Unió közötti átfo","2017.09.21","","EU"],["142","5500","","U126","Származásmegjelölő nyilatkozat (az EU-Mercosur ideiglenes kereskedelmi megállapo","2026.05.01","2026.12.31","EU"],["711","KP","","Y920","Az intézkedéshez kapcsolt lábjegyzetben szereplő termékektől eltérő termék","2017.09.01","","EU"],["761","1011","","Y110","Mentesség a REACH rendelet szerinti korlátozások alól az 1907/2006 rendelet 67. ","2025.06.23","","EU"],["761","1011","","Y106","Megfelelés az 1907/2006 rendelet XVII. mellékletének 2. oszlopában meghatározott","2025.06.23","","EU"],["761","1011","","Y113","Az 1907/2006/EK rendelet rendelkezéseinek hatálya alá nem tartozó anyag/keverék.","2025.06.23","","EU"]]}